zelden/__init__.py
zelden/mechanics_test.py
zelden/src/__init__.py
zelden/src/consts.py
zelden/src/credentials.py
zelden/src/exceptions.py
zelden/src/randomizer.py
zelden/src/set_json.py
Zelden-0.0.4.dist-info/LICENSE
Zelden-0.0.4.dist-info/METADATA
Zelden-0.0.4.dist-info/WHEEL
Zelden-0.0.4.dist-info/top_level.txt
Zelden-0.0.4.dist-info/RECORD
