Metadata-Version: 2.1
Name: Zelden
Version: 0.0.4
Summary: A True Random Generator Package
Author-email: Victor Kolis <victorkolis@protonmail.com>
Maintainer-email: Victor Kolis <victorkolis@protonmail.com>
Project-URL: Homepage, https://github.com/Pynosaur/zelden
Project-URL: Bug Tracker, https://github.com/Pynosaur/zelden/issues
Classifier: Programming Language :: Python :: 3
Classifier: License :: OSI Approved :: MIT License
Classifier: Operating System :: OS Independent
Requires-Python: >=3.10
License-File: LICENSE
Requires-Dist: requests
